{
  "annotations": {
    "list": [
      {
        "builtIn": 1,
        "datasource": {
          "type": "grafana",
          "uid": "-- Grafana --"
        },
        "enable": true,
        "hide": true,
        "iconColor": "rgba(0, 211, 255, 1)",
        "name": "Annotations & Alerts",
        "target": {
          "limit": 100,
          "matchAny": false,
          "tags": [],
          "type": "dashboard"
        },
        "type": "dashboard"
      }
    ]
  },
  "editable": true,
  "fiscalYearStartMonth": 0,
  "graphTooltip": 0,
  "id": 1,
  "links": [],
  "liveNow": false,
  "panels": [
    {
      "datasource": {
        "type": "frser-sqlite-datasource",
        "uid": "P0CD8666848BF286D"
      },
      "description": "0 -> Very Cheap\n1 -> Cheap\n2 -> Expensive\n3 -> Very Expensive",
      "fieldConfig": {
        "defaults": {
          "color": {
            "mode": "continuous-GrYlRd"
          },
          "custom": {
            "axisGridShow": true,
            "axisLabel": "0 -> Very Cheap | 1 -> Cheap | 2 -> Expensive | 3 -> Very Expensive",
            "axisPlacement": "right",
            "axisSoftMin": 0,
            "fillOpacity": 85,
            "gradientMode": "hue",
            "hideFrom": {
              "legend": false,
              "tooltip": false,
              "viz": false
            },
            "lineWidth": 2,
            "scaleDistribution": {
              "type": "linear"
            }
          },
          "mappings": [],
          "max": 3,
          "min": 0,
          "thresholds": {
            "mode": "absolute",
            "steps": [
              {
                "color": "green",
                "value": null
              },
              {
                "color": "red",
                "value": 80
              }
            ]
          },
          "unit": "none"
        },
        "overrides": []
      },
      "gridPos": {
        "h": 8,
        "w": 20,
        "x": 0,
        "y": 0
      },
      "id": 5,
      "options": {
        "barRadius": 0,
        "barWidth": 0.86,
        "colorByField": "prediction",
        "groupWidth": 0.7,
        "legend": {
          "calcs": [],
          "displayMode": "list",
          "placement": "right"
        },
        "orientation": "horizontal",
        "showValue": "always",
        "stacking": "none",
        "text": {},
        "tooltip": {
          "mode": "single",
          "sort": "none"
        },
        "xTickLabelRotation": 0,
        "xTickLabelSpacing": 0
      },
      "targets": [
        {
          "datasource": {
            "type": "frser-sqlite-datasource",
            "uid": "BEfq0gqnz"
          },
          "queryText": "SELECT prediction, datetime FROM predictions\norder by datetime;",
          "queryType": "table",
          "rawQueryText": "SELECT prediction, datetime FROM predictions\norder by datetime;",
          "refId": "A",
          "timeColumns": [
            "time",
            "ts"
          ]
        }
      ],
      "title": "Predictions",
      "type": "barchart"
    },
    {
      "datasource": {
        "type": "frser-sqlite-datasource",
        "uid": "P0CD8666848BF286D"
      },
      "fieldConfig": {
        "defaults": {
          "mappings": [],
          "max": 100,
          "min": 0,
          "thresholds": {
            "mode": "percentage",
            "steps": [
              {
                "color": "green",
                "value": null
              },
              {
                "color": "red",
                "value": 80
              }
            ]
          }
        },
        "overrides": []
      },
      "gridPos": {
        "h": 8,
        "w": 4,
        "x": 20,
        "y": 0
      },
      "id": 3,
      "options": {
        "orientation": "auto",
        "reduceOptions": {
          "calcs": [
            "lastNotNull"
          ],
          "fields": "",
          "values": false
        },
        "showThresholdLabels": false,
        "showThresholdMarkers": true
      },
      "pluginVersion": "9.0.0",
      "targets": [
        {
          "datasource": {
            "type": "frser-sqlite-datasource",
            "uid": "BEfq0gqnz"
          },
          "queryText": "SELECT count(prediction) FROM predictions;",
          "queryType": "table",
          "rawQueryText": "SELECT count(prediction) FROM predictions;",
          "refId": "A",
          "timeColumns": [
            "time",
            "ts"
          ]
        }
      ],
      "title": "Total Prediction Count",
      "type": "gauge"
    },
    {
      "datasource": {
        "type": "frser-sqlite-datasource",
        "uid": "P0CD8666848BF286D"
      },
      "fieldConfig": {
        "defaults": {
          "color": {
            "mode": "thresholds"
          },
          "custom": {
            "axisLabel": "",
            "axisPlacement": "auto",
            "axisSoftMin": 0,
            "fillOpacity": 80,
            "gradientMode": "none",
            "hideFrom": {
              "legend": false,
              "tooltip": false,
              "viz": false
            },
            "lineWidth": 1,
            "scaleDistribution": {
              "type": "linear"
            }
          },
          "mappings": [],
          "thresholds": {
            "mode": "absolute",
            "steps": [
              {
                "color": "green",
                "value": null
              },
              {
                "color": "red",
                "value": 80
              }
            ]
          }
        },
        "overrides": [
          {
            "matcher": {
              "id": "byName",
              "options": "Primary Camera"
            },
            "properties": [
              {
                "id": "color",
                "value": {
                  "fixedColor": "yellow",
                  "mode": "fixed"
                }
              }
            ]
          },
          {
            "matcher": {
              "id": "byName",
              "options": "id"
            },
            "properties": [
              {
                "id": "color",
                "value": {
                  "fixedColor": "orange",
                  "mode": "fixed"
                }
              }
            ]
          },
          {
            "matcher": {
              "id": "byName",
              "options": "Ram"
            },
            "properties": [
              {
                "id": "color",
                "value": {
                  "fixedColor": "orange",
                  "mode": "fixed"
                }
              }
            ]
          }
        ]
      },
      "gridPos": {
        "h": 8,
        "w": 12,
        "x": 0,
        "y": 8
      },
      "id": 7,
      "options": {
        "barRadius": 0,
        "barWidth": 0.97,
        "groupWidth": 0.7,
        "legend": {
          "calcs": [],
          "displayMode": "list",
          "placement": "bottom"
        },
        "orientation": "auto",
        "showValue": "auto",
        "stacking": "none",
        "tooltip": {
          "mode": "single",
          "sort": "none"
        },
        "xTickLabelRotation": 0,
        "xTickLabelSpacing": 0
      },
      "targets": [
        {
          "datasource": {
            "type": "frser-sqlite-datasource",
            "uid": "P0CD8666848BF286D"
          },
          "queryText": "SELECT\n  ram as 'Ram',\n  id\nFROM predictions\ngroup by id\norder by id;",
          "queryType": "table",
          "rawQueryText": "SELECT\n  ram as 'Ram',\n  id\nFROM predictions\ngroup by id\norder by id;",
          "refId": "A",
          "timeColumns": [
            "datetime",
            "id"
          ]
        }
      ],
      "title": "Ram Distribution ",
      "type": "barchart"
    },
    {
      "datasource": {
        "type": "frser-sqlite-datasource",
        "uid": "P0CD8666848BF286D"
      },
      "fieldConfig": {
        "defaults": {
          "color": {
            "mode": "thresholds"
          },
          "custom": {
            "axisLabel": "",
            "axisPlacement": "auto",
            "axisSoftMin": 0,
            "fillOpacity": 80,
            "gradientMode": "none",
            "hideFrom": {
              "legend": false,
              "tooltip": false,
              "viz": false
            },
            "lineWidth": 1,
            "scaleDistribution": {
              "type": "linear"
            }
          },
          "mappings": [],
          "thresholds": {
            "mode": "absolute",
            "steps": [
              {
                "color": "green",
                "value": null
              },
              {
                "color": "red",
                "value": 80
              }
            ]
          }
        },
        "overrides": [
          {
            "matcher": {
              "id": "byName",
              "options": "Primary Camera"
            },
            "properties": [
              {
                "id": "color",
                "value": {
                  "fixedColor": "yellow",
                  "mode": "fixed"
                }
              }
            ]
          },
          {
            "matcher": {
              "id": "byName",
              "options": "id"
            },
            "properties": [
              {
                "id": "color",
                "value": {
                  "fixedColor": "orange",
                  "mode": "fixed"
                }
              }
            ]
          },
          {
            "matcher": {
              "id": "byName",
              "options": "Ram"
            },
            "properties": [
              {
                "id": "color",
                "value": {
                  "fixedColor": "orange",
                  "mode": "fixed"
                }
              }
            ]
          },
          {
            "matcher": {
              "id": "byName",
              "options": "Number of Cores"
            },
            "properties": [
              {
                "id": "color",
                "value": {
                  "fixedColor": "blue",
                  "mode": "fixed"
                }
              }
            ]
          }
        ]
      },
      "gridPos": {
        "h": 8,
        "w": 12,
        "x": 12,
        "y": 8
      },
      "id": 8,
      "options": {
        "barRadius": 0,
        "barWidth": 0.97,
        "groupWidth": 0.7,
        "legend": {
          "calcs": [],
          "displayMode": "list",
          "placement": "bottom"
        },
        "orientation": "auto",
        "showValue": "auto",
        "stacking": "none",
        "tooltip": {
          "mode": "single",
          "sort": "none"
        },
        "xTickLabelRotation": 0,
        "xTickLabelSpacing": 0
      },
      "targets": [
        {
          "datasource": {
            "type": "frser-sqlite-datasource",
            "uid": "P0CD8666848BF286D"
          },
          "queryText": "SELECT\n  numcores as 'Number of Cores',\n  id\nFROM predictions\ngroup by id\norder by id;",
          "queryType": "table",
          "rawQueryText": "SELECT\n  numcores as 'Number of Cores',\n  id\nFROM predictions\ngroup by id\norder by id;",
          "refId": "A",
          "timeColumns": [
            "datetime",
            "id"
          ]
        }
      ],
      "title": "Core Numbers Distribution",
      "type": "barchart"
    },
    {
      "datasource": {
        "type": "frser-sqlite-datasource",
        "uid": "P0CD8666848BF286D"
      },
      "fieldConfig": {
        "defaults": {
          "color": {
            "mode": "thresholds"
          },
          "custom": {
            "axisLabel": "",
            "axisPlacement": "auto",
            "axisSoftMin": 0,
            "fillOpacity": 80,
            "gradientMode": "none",
            "hideFrom": {
              "legend": false,
              "tooltip": false,
              "viz": false
            },
            "lineWidth": 1,
            "scaleDistribution": {
              "type": "linear"
            }
          },
          "mappings": [],
          "thresholds": {
            "mode": "absolute",
            "steps": [
              {
                "color": "green",
                "value": null
              },
              {
                "color": "red",
                "value": 80
              }
            ]
          }
        },
        "overrides": [
          {
            "matcher": {
              "id": "byName",
              "options": "Primary Camera"
            },
            "properties": [
              {
                "id": "color",
                "value": {
                  "fixedColor": "yellow",
                  "mode": "fixed"
                }
              }
            ]
          },
          {
            "matcher": {
              "id": "byName",
              "options": "id"
            },
            "properties": [
              {
                "id": "color",
                "value": {
                  "fixedColor": "orange",
                  "mode": "fixed"
                }
              }
            ]
          },
          {
            "matcher": {
              "id": "byName",
              "options": "Ram"
            },
            "properties": [
              {
                "id": "color",
                "value": {
                  "fixedColor": "orange",
                  "mode": "fixed"
                }
              }
            ]
          },
          {
            "matcher": {
              "id": "byName",
              "options": "Number of Cores"
            },
            "properties": [
              {
                "id": "color",
                "value": {
                  "fixedColor": "blue",
                  "mode": "fixed"
                }
              }
            ]
          }
        ]
      },
      "gridPos": {
        "h": 8,
        "w": 12,
        "x": 0,
        "y": 16
      },
      "id": 9,
      "options": {
        "barRadius": 0,
        "barWidth": 0.97,
        "groupWidth": 0.7,
        "legend": {
          "calcs": [],
          "displayMode": "list",
          "placement": "bottom"
        },
        "orientation": "auto",
        "showValue": "auto",
        "stacking": "none",
        "tooltip": {
          "mode": "single",
          "sort": "none"
        },
        "xTickLabelRotation": 0,
        "xTickLabelSpacing": 0
      },
      "targets": [
        {
          "datasource": {
            "type": "frser-sqlite-datasource",
            "uid": "P0CD8666848BF286D"
          },
          "queryText": "SELECT\n  pc as 'Primary Camera',\n  id\nFROM predictions\ngroup by id\norder by id;",
          "queryType": "table",
          "rawQueryText": "SELECT\n  pc as 'Primary Camera',\n  id\nFROM predictions\ngroup by id\norder by id;",
          "refId": "A",
          "timeColumns": [
            "datetime",
            "id"
          ]
        }
      ],
      "title": "Primary Camera Distribution",
      "type": "barchart"
    },
    {
      "datasource": {
        "type": "frser-sqlite-datasource",
        "uid": "P0CD8666848BF286D"
      },
      "fieldConfig": {
        "defaults": {
          "color": {
            "mode": "thresholds"
          },
          "custom": {
            "axisLabel": "",
            "axisPlacement": "auto",
            "axisSoftMin": 0,
            "fillOpacity": 80,
            "gradientMode": "none",
            "hideFrom": {
              "legend": false,
              "tooltip": false,
              "viz": false
            },
            "lineWidth": 1,
            "scaleDistribution": {
              "type": "linear"
            }
          },
          "mappings": [],
          "thresholds": {
            "mode": "absolute",
            "steps": [
              {
                "color": "green",
                "value": null
              },
              {
                "color": "red",
                "value": 80
              }
            ]
          }
        },
        "overrides": [
          {
            "matcher": {
              "id": "byName",
              "options": "Primary Camera"
            },
            "properties": [
              {
                "id": "color",
                "value": {
                  "fixedColor": "yellow",
                  "mode": "fixed"
                }
              }
            ]
          },
          {
            "matcher": {
              "id": "byName",
              "options": "id"
            },
            "properties": [
              {
                "id": "color",
                "value": {
                  "fixedColor": "orange",
                  "mode": "fixed"
                }
              }
            ]
          },
          {
            "matcher": {
              "id": "byName",
              "options": "Ram"
            },
            "properties": [
              {
                "id": "color",
                "value": {
                  "fixedColor": "orange",
                  "mode": "fixed"
                }
              }
            ]
          },
          {
            "matcher": {
              "id": "byName",
              "options": "Number of Cores"
            },
            "properties": [
              {
                "id": "color",
                "value": {
                  "fixedColor": "blue",
                  "mode": "fixed"
                }
              }
            ]
          }
        ]
      },
      "gridPos": {
        "h": 8,
        "w": 12,
        "x": 12,
        "y": 16
      },
      "id": 10,
      "options": {
        "barRadius": 0,
        "barWidth": 0.97,
        "groupWidth": 0.7,
        "legend": {
          "calcs": [],
          "displayMode": "list",
          "placement": "bottom"
        },
        "orientation": "auto",
        "showValue": "auto",
        "stacking": "none",
        "tooltip": {
          "mode": "single",
          "sort": "none"
        },
        "xTickLabelRotation": 0,
        "xTickLabelSpacing": 0
      },
      "targets": [
        {
          "datasource": {
            "type": "frser-sqlite-datasource",
            "uid": "P0CD8666848BF286D"
          },
          "queryText": "SELECT\n  intmemory as 'Internal Memory',\n  id\nFROM predictions\ngroup by id\norder by id;",
          "queryType": "table",
          "rawQueryText": "SELECT\n  intmemory as 'Internal Memory',\n  id\nFROM predictions\ngroup by id\norder by id;",
          "refId": "A",
          "timeColumns": [
            "datetime",
            "id"
          ]
        }
      ],
      "title": "Internal Memory Distribution",
      "type": "barchart"
    },
    {
      "datasource": {
        "type": "frser-sqlite-datasource",
        "uid": "P0CD8666848BF286D"
      },
      "fieldConfig": {
        "defaults": {
          "color": {
            "mode": "thresholds"
          },
          "custom": {
            "align": "auto",
            "displayMode": "auto",
            "inspect": false
          },
          "mappings": [],
          "thresholds": {
            "mode": "absolute",
            "steps": [
              {
                "color": "green",
                "value": null
              },
              {
                "color": "red",
                "value": 80
              }
            ]
          }
        },
        "overrides": []
      },
      "gridPos": {
        "h": 11,
        "w": 24,
        "x": 0,
        "y": 24
      },
      "id": 1,
      "options": {
        "footer": {
          "fields": "",
          "reducer": [
            "sum"
          ],
          "show": false
        },
        "showHeader": true
      },
      "pluginVersion": "9.0.0",
      "targets": [
        {
          "datasource": {
            "type": "frser-sqlite-datasource",
            "uid": "BEfq0gqnz"
          },
          "key": "Q-e10c6193-a544-43ed-b8b7-f08e01b9dde2-0",
          "queryText": "SELECT \n  id as 'ID', \n  datetime as 'Datetime',\n  ram as 'Ram',\n  numcores as 'Number of Cores',\n  intmemory as 'Internal Memory',\n  pc as 'Primary Camera',\n  prediction as 'Prediction'\nFROM predictions;\n",
          "queryType": "table",
          "rawQueryText": "SELECT \n  id as 'ID', \n  datetime as 'Datetime',\n  ram as 'Ram',\n  numcores as 'Number of Cores',\n  intmemory as 'Internal Memory',\n  pc as 'Primary Camera',\n  prediction as 'Prediction'\nFROM predictions;\n",
          "refId": "A",
          "timeColumns": [
            "time",
            "ts"
          ]
        }
      ],
      "title": "Detailed Predictions Table",
      "type": "table"
    }
  ],
  "refresh": "",
  "schemaVersion": 36,
  "style": "dark",
  "tags": [],
  "templating": {
    "list": []
  },
  "time": {
    "from": "now-30d",
    "to": "now"
  },
  "timepicker": {},
  "timezone": "",
  "title": "Prediction App Metrics",
  "uid": "c5D5JR3nz",
  "version": 7,
  "weekStart": ""
}